<?xml version="1.0" encoding="utf-8" ?>
<dwsync>
<file name="1.jpg" server="ftp.canueza.com" local="132108362533439889" remote="132167897400000000" Dst="2" />
<file name="10.jpg" server="ftp.canueza.com" local="132108362533699928" remote="132167897400000000" Dst="2" />
<file name="11.jpg" server="ftp.canueza.com" local="132108362534009914" remote="132167897400000000" Dst="2" />
<file name="12.jpg" server="ftp.canueza.com" local="132108362534369928" remote="132167897400000000" Dst="2" />
<file name="13.jpg" server="ftp.canueza.com" local="132108362534789913" remote="132167897400000000" Dst="2" />
<file name="14.jpg" server="ftp.canueza.com" local="132108362535210136" remote="132167897400000000" Dst="2" />
<file name="2.jpg" server="ftp.canueza.com" local="132108362535509903" remote="132167897400000000" Dst="2" />
<file name="4.jpg" server="ftp.canueza.com" local="132108362536119910" remote="132167897400000000" Dst="2" />
<file name="3.jpg" server="ftp.canueza.com" local="132108362535799913" remote="132167897400000000" Dst="2" />
<file name="6.jpg" server="ftp.canueza.com" local="132108362536579904" remote="132167897400000000" Dst="2" />
<file name="5.jpg" server="ftp.canueza.com" local="132108362536309978" remote="132167897400000000" Dst="2" />
<file name="7.jpg" server="ftp.canueza.com" local="132108362536799880" remote="132167897400000000" Dst="2" />
<file name="8.jpg" server="ftp.canueza.com" local="132108362537029919" remote="132167897400000000" Dst="2" />
<file name="9.jpg" server="ftp.canueza.com" local="132108362537329937" remote="132167897400000000" Dst="2" />
<file name="1.jpg" server="ftp.canueza.com//" local="132108362533439889" remote="132169551600000000" Dst="2" />
<file name="10.jpg" server="ftp.canueza.com//" local="132108362533699928" remote="132169551600000000" Dst="2" />
<file name="11.jpg" server="ftp.canueza.com//" local="132108362534009914" remote="132169551600000000" Dst="2" />
<file name="12.jpg" server="ftp.canueza.com//" local="132108362534369928" remote="132169551600000000" Dst="2" />
<file name="13.jpg" server="ftp.canueza.com//" local="132108362534789913" remote="132169551600000000" Dst="2" />
<file name="14.jpg" server="ftp.canueza.com//" local="132108362535210136" remote="132169551600000000" Dst="2" />
<file name="2.jpg" server="ftp.canueza.com//" local="132108362535509903" remote="132169551600000000" Dst="2" />
<file name="4.jpg" server="ftp.canueza.com//" local="132108362536119910" remote="132169551600000000" Dst="2" />
<file name="3.jpg" server="ftp.canueza.com//" local="132108362535799913" remote="132169551600000000" Dst="2" />
<file name="5.jpg" server="ftp.canueza.com//" local="132108362536309978" remote="132169551600000000" Dst="2" />
<file name="6.jpg" server="ftp.canueza.com//" local="132108362536579904" remote="132169551600000000" Dst="2" />
<file name="7.jpg" server="ftp.canueza.com//" local="132108362536799880" remote="132169551600000000" Dst="2" />
<file name="8.jpg" server="ftp.canueza.com//" local="132108362537029919" remote="132169551600000000" Dst="2" />
<file name="9.jpg" server="ftp.canueza.com//" local="132108362537329937" remote="132169551600000000" Dst="2" />
<file name="1.jpg" server="ftp.canueza.com//www/" local="132108362533439889" remote="132169555200000000" Dst="2" />
<file name="10.jpg" server="ftp.canueza.com//www/" local="132108362533699928" remote="132169555200000000" Dst="2" />
<file name="12.jpg" server="ftp.canueza.com//www/" local="132108362534369928" remote="132169555200000000" Dst="2" />
<file name="11.jpg" server="ftp.canueza.com//www/" local="132108362534009914" remote="132169555200000000" Dst="2" />
<file name="13.jpg" server="ftp.canueza.com//www/" local="132108362534789913" remote="132169555200000000" Dst="2" />
<file name="2.jpg" server="ftp.canueza.com//www/" local="132108362535509903" remote="132169555200000000" Dst="2" />
<file name="14.jpg" server="ftp.canueza.com//www/" local="132108362535210136" remote="132169555200000000" Dst="2" />
<file name="4.jpg" server="ftp.canueza.com//www/" local="132108362536119910" remote="132169555200000000" Dst="2" />
<file name="5.jpg" server="ftp.canueza.com//www/" local="132108362536309978" remote="132169555200000000" Dst="2" />
<file name="3.jpg" server="ftp.canueza.com//www/" local="132108362535799913" remote="132169555200000000" Dst="2" />
<file name="6.jpg" server="ftp.canueza.com//www/" local="132108362536579904" remote="132169555200000000" Dst="2" />
<file name="7.jpg" server="ftp.canueza.com//www/" local="132108362536799880" remote="132169555200000000" Dst="2" />
<file name="8.jpg" server="ftp.canueza.com//www/" local="132108362537029919" remote="132169555200000000" Dst="2" />
<file name="9.jpg" server="ftp.canueza.com//www/" local="132108362537329937" remote="132169555200000000" Dst="2" />
<file name="Linkedin-HeadShot-BrianLabelle.jpg" server="ftp.canueza.com//www/" local="131145676300000000" remote="132174846000000000" Dst="1" />
</dwsync>